Metadata-Version: 2.1
Name: etsy3py
Version: 0.0.3
Summary: ETSY API v3 Client
Home-page: https://github.com/damhuman/Etsy3Py
Author: Anton Dasyuk
Author-email: anton.dasyuk@gmail.com
Maintainer: Ali-Abdulla Al-Sayed
Maintainer-email: alexukr1999@gmail.com
License: MIT
Keywords: etsy,api,client,etsy v3 api
Platform: UNKNOWN
Classifier: Programming Language :: Python :: 3
Classifier: Development Status :: 4 - Beta
Classifier: License :: OSI Approved :: MIT License
Requires-Python: >=3.6
License-File: LICENSE.txt
